README.md
geewiz/__init__.py
geewiz/client.py
geewiz/progress.py
geewiz-0.2.0.dist-info/METADATA
geewiz-0.2.0.dist-info/WHEEL
geewiz-0.2.0.dist-info/RECORD
