Metadata-Version: 2.1
Name: geewiz
Version: 0.2.0
Summary: 
License: UNLICENSED
Author: Mike Nicholaides
Author-email: mike.nicholaides@gmail.com
Requires-Python: >=3.9,<4.0
Classifier: License :: Other/Proprietary License
Classifier: Programming Language :: Python :: 3
Classifier: Programming Language :: Python :: 3.9
Classifier: Programming Language :: Python :: 3.10
Classifier: Programming Language :: Python :: 3.11
Classifier: Programming Language :: Python :: 3.12
